ntcir_math_density/__init__.py
ntcir_math_density/__main__.py
ntcir_math_density/estimator.py
ntcir_math_density/view.py
ntcir_math_density-0.2.1.dist-info/LICENSE.txt
ntcir_math_density-0.2.1.dist-info/METADATA
ntcir_math_density-0.2.1.dist-info/RECORD
ntcir_math_density-0.2.1.dist-info/WHEEL
ntcir_math_density-0.2.1.dist-info/entry_points.txt
ntcir_math_density-0.2.1.dist-info/top_level.txt
