Metadata-Version: 2.1
Name: ntcir-math-density
Version: 0.2.1
Summary: 
Home-page: https://github.com/MIR-MU/ntcir-math-density
Author: Vit Novotny
Maintainer: Vit Novotny
License: MIT
Project-URL: Source, https://github.com/MIR-MU/ntcir-math-density
Keywords: ntcir math_information_retrieval
Platform: UNKNOWN
Classifier: Development Status :: 4 - Beta
Classifier: Environment :: Console
Classifier: Intended Audience :: Science/Research
Classifier: License :: OSI Approved :: MIT License
Classifier: Operating System :: OS Independent
Classifier: Programming Language :: Python :: 3.4
Classifier: Topic :: Scientific/Engineering :: Mathematics
Classifier: Topic :: Text Processing :: Markup :: XML
Requires-Python: ~= 3.4
Requires-Dist: matplotlib (~=2.2.2)
Requires-Dist: numpy (~=1.14.3)
Requires-Dist: scikit-learn (~=0.19.1)
Requires-Dist: scipy (~=1.1.0)
Requires-Dist: tqdm (~=4.23.3)
